setup.py
simple_distributions_v01/Binomialdistribution.py
simple_distributions_v01/Gaussiandistribution.py
simple_distributions_v01/Generaldistribution.py
simple_distributions_v01/__init__.py
simple_distributions_v01.egg-info/PKG-INFO
simple_distributions_v01.egg-info/SOURCES.txt
simple_distributions_v01.egg-info/dependency_links.txt
simple_distributions_v01.egg-info/not-zip-safe
simple_distributions_v01.egg-info/top_level.txt