Metadata-Version: 1.0
Name: simple-distributions-v01
Version: 1.0
Summary: Gaussian and Binomial distributions
Home-page: UNKNOWN
Author: Kashyaph
Author-email: UNKNOWN
License: UNKNOWN
Platform: UNKNOWN
